gedcomx/__init__.py
gedcomx/date.py
gedcomx/enums.py
gedcomx/fileformat.py
gedcomx/models.py
gedcomx/reader.py
gedcomx/record.py
gedcomx/utils.py
gedcomx_python-0.1.6.dist-info/LICENSE
gedcomx_python-0.1.6.dist-info/METADATA
gedcomx_python-0.1.6.dist-info/WHEEL
gedcomx_python-0.1.6.dist-info/RECORD
